autofit/__init__.py
autofit/conf.py
autofit/exc.py
autofit/fixtures.py
autofit/mock.py
autofit/visualise.py
autofit/aggregator/__init__.py
autofit/aggregator/aggregator.py
autofit/aggregator/base.py
autofit/aggregator/file_output.py
autofit/aggregator/fit_interface.py
autofit/aggregator/predicate.py
autofit/aggregator/search_output.py
autofit/aggregator/summary/__init__.py
autofit/aggregator/summary/aggregate_fits.py
autofit/aggregator/summary/aggregate_images.py
autofit/aggregator/summary/aggregate_csv/__init__.py
autofit/aggregator/summary/aggregate_csv/column.py
autofit/aggregator/summary/aggregate_csv/row.py
autofit/config/.gitignore
autofit/config/README.rst
autofit/config/general.yaml
autofit/config/logging.yaml
autofit/config/notation.yaml
autofit/config/output.yaml
autofit/config/non_linear/GridSearch.yaml
autofit/config/non_linear/README.rst
autofit/config/non_linear/mcmc.yaml
autofit/config/non_linear/mle.yaml
autofit/config/non_linear/nest.yaml
autofit/config/priors/Exponential.yaml
autofit/config/priors/Gaussian.yaml
autofit/config/priors/Gaussian2D.yaml
autofit/config/priors/GaussianKurtosis.yaml
autofit/config/priors/MultiLevelGaussians.yaml
autofit/config/priors/README.rst
autofit/config/priors/model.yaml
autofit/config/priors/prior.yaml
autofit/config/priors/profiles.yaml
autofit/config/priors/template.yaml
autofit/config/visualize/README.rst
autofit/config/visualize/general.yaml
autofit/config/visualize/plots_search.yaml
autofit/config/visualize/plots_settings.yaml
autofit/database/__init__.py
autofit/database/sqlalchemy_.py
autofit/database/aggregator/__init__.py
autofit/database/aggregator/aggregator.py
autofit/database/aggregator/info.py
autofit/database/aggregator/scrape.py
autofit/database/migration/__init__.py
autofit/database/migration/migration.py
autofit/database/migration/session_wrapper.py
autofit/database/migration/steps.py
autofit/database/model/__init__.py
autofit/database/model/array.py
autofit/database/model/common.py
autofit-2026.1.21.3.dist-info/licenses/LICENSE
autofit-2026.1.21.3.dist-info/METADATA
autofit-2026.1.21.3.dist-info/WHEEL
autofit-2026.1.21.3.dist-info/top_level.txt
autofit-2026.1.21.3.dist-info/RECORD
