Metadata-Version: 2.4
Name: autofit
Version: 2026.1.21.3
Summary: Classy Probabilistic Programming
Author-email: James Nightingale <James.Nightingale@newcastle.ac.uk>, Richard Hayes <richard@rghsoftware.co.uk>
License: MIT
Project-URL: Homepage, https://github.com/rhayes777/PyAutoFit
Keywords: cli
Classifier: Intended Audience :: Science/Research
Classifier: Topic :: Scientific/Engineering :: Physics
Classifier: Natural Language :: English
Classifier: Operating System :: OS Independent
Classifier: Programming Language :: Python :: 3.9
Classifier: Programming Language :: Python :: 3.10
Classifier: Programming Language :: Python :: 3.11
Classifier: Programming Language :: Python :: 3.12
Requires-Python: >=3.9
License-File: LICENSE
Requires-Dist: autoconf
Requires-Dist: array_api_compat
Requires-Dist: anesthetic==2.8.14
Requires-Dist: corner==2.2.2
Requires-Dist: decorator>=4.2.1
Requires-Dist: dill>=0.3.1.1
Requires-Dist: dynesty==2.1.4
Requires-Dist: typing-inspect>=0.4.0
Requires-Dist: emcee>=3.1.6
Requires-Dist: gprof2dot==2021.2.21
Requires-Dist: matplotlib
Requires-Dist: numpydoc>=1.0.0
Requires-Dist: pyprojroot==0.2.0
Requires-Dist: pyswarms==1.3.0
Requires-Dist: h5py>=3.11.0
Requires-Dist: SQLAlchemy==2.0.32
Requires-Dist: scipy<=1.14.0
Requires-Dist: astunparse==1.6.3
Requires-Dist: threadpoolctl<=3.2.0,>=3.1.0
Requires-Dist: timeout-decorator==0.5.0
Requires-Dist: xxhash<=3.4.1
Requires-Dist: networkx==3.1
Requires-Dist: pyvis==0.3.2
Requires-Dist: psutil==6.1.0
Provides-Extra: optional
Requires-Dist: astropy>=5.0; extra == "optional"
Requires-Dist: getdist==1.4; extra == "optional"
Requires-Dist: nautilus-sampler==1.0.5; extra == "optional"
Requires-Dist: ultranest==4.3.2; extra == "optional"
Requires-Dist: zeus-mcmc==2.5.4; extra == "optional"
Provides-Extra: docs
Requires-Dist: sphinx; extra == "docs"
Requires-Dist: furo; extra == "docs"
Requires-Dist: myst-parser; extra == "docs"
Requires-Dist: sphinx_copybutton; extra == "docs"
Requires-Dist: sphinx_design; extra == "docs"
Requires-Dist: sphinx_inline_tabs; extra == "docs"
Requires-Dist: sphinx_autodoc_typehints; extra == "docs"
Provides-Extra: test
Requires-Dist: pytest; extra == "test"
Provides-Extra: dev
Requires-Dist: pytest; extra == "dev"
Requires-Dist: black; extra == "dev"
Dynamic: license-file
